LICENSE
README.md
setup.cfg
setup.py
modelTissueFlow/__init__.py
modelTissueFlow/modelTissueFlow.py
modelTissueFlow.egg-info/PKG-INFO
modelTissueFlow.egg-info/SOURCES.txt
modelTissueFlow.egg-info/dependency_links.txt
modelTissueFlow.egg-info/not-zip-safe
modelTissueFlow.egg-info/requires.txt
modelTissueFlow.egg-info/top_level.txt
modelTissueFlow/modules/__init__.py
modelTissueFlow/modules/inOutTools.py
modelTissueFlow/modules/processPIV/PIV.c
modelTissueFlow/modules/processPIV/PIV.pyx