Metadata-Version: 2.1
Name: modelTissueFlow
Version: 3.1
Summary: tissue-flow-analysis
Home-page: https://github.com/HiBandan/modelTissueFlow
Author: Bandan Chakrabortty
Author-email: bandan13@gmail.com
License-File: LICENSE
